LICENSE
mongorunway/__init__.py
mongorunway/api.py
mongorunway/application/__init__.py
mongorunway/application/applications.py
mongorunway/application/config.py
mongorunway/application/event_manager.py
mongorunway/application/filesystem.py
mongorunway/application/output.py
mongorunway/application/ports/__init__.py
mongorunway/application/ports/auditlog_journal.py
mongorunway/application/ports/config_reader.py
mongorunway/application/ports/filename_strategy.py
mongorunway/application/ports/repository.py
mongorunway/application/services/__init__.py
mongorunway/application/services/checksum_service.py
mongorunway/application/services/migration_service.py
mongorunway/application/services/status_service.py
mongorunway/application/services/validation_service.py
mongorunway/application/services/versioning_service.py
mongorunway/application/session.py
mongorunway/application/traits.py
mongorunway/application/transactions.py
mongorunway/application/use_cases.py
mongorunway/application/ux.py
mongorunway/domain/__init__.py
mongorunway/domain/migration.py
mongorunway/domain/migration_auditlog_entry.py
mongorunway/domain/migration_business_module.py
mongorunway/domain/migration_business_rule.py
mongorunway/domain/migration_command.py
mongorunway/domain/migration_context.py
mongorunway/domain/migration_event.py
mongorunway/domain/migration_event_manager.py
mongorunway/domain/migration_exception.py
mongorunway/infrastructure/__init__.py
mongorunway/infrastructure/commands.py
mongorunway/infrastructure/config_readers.py
mongorunway/infrastructure/event_handlers.py
mongorunway/infrastructure/filename_strategies.py
mongorunway/infrastructure/persistence/__init__.py
mongorunway/infrastructure/persistence/auditlog_journals.py
mongorunway/infrastructure/persistence/repositories.py
mongorunway/mongo.py
mongorunway/presentation/__init__.py
mongorunway/presentation/cli.py
mongorunway/presentation/formatters.py
mongorunway/presentation/presenters.py
mongorunway/util.py
mongorunway-1.0.7a0.dist-info/entry_points.txt
mongorunway-1.0.7a0.dist-info/LICENSE
mongorunway-1.0.7a0.dist-info/METADATA
mongorunway-1.0.7a0.dist-info/WHEEL
mongorunway-1.0.7a0.dist-info/RECORD
