Metadata-Version: 2.1
Name: mongorunway
Version: 1.0.7a0
Summary: A MongoDB migration tool.
Home-page: https://github.com/Animatea/mongorunway
License: MIT
Keywords: migration,mongodb,mongo,mongorunway
Author: Animatea
Author-email: animatea.programming@gmail.com
Requires-Python: >=3.9,<4.0
Classifier: Intended Audience :: Developers
Classifier: License :: OSI Approved :: MIT License
Classifier: Natural Language :: English
Classifier: Operating System :: OS Independent
Classifier: Programming Language :: Python :: 3
Classifier: Programming Language :: Python :: 3.9
Classifier: Programming Language :: Python :: 3.10
Classifier: Programming Language :: Python :: 3.11
Classifier: Programming Language :: Python :: Implementation :: CPython
Classifier: Topic :: Software Development :: Libraries
Classifier: Topic :: Software Development :: Libraries :: Python Modules
Classifier: Topic :: Utilities
Classifier: Typing :: Typed
Requires-Dist: PyYAML (==6.0.0)
Requires-Dist: attrs (==23.1.0)
Requires-Dist: click (==8.1.3)
Requires-Dist: pymongo (==4.3.3)
Requires-Dist: terminaltables (==3.1.10)
Requires-Dist: typing_extensions (==4.5.0)
Requires-Dist: tzdata (==2023.3)
Project-URL: Bug Tracker, https://github.com/Animatea/mongorunway/issues
Project-URL: Documentation, https://animatea.github.io/mongorunway/
Project-URL: Repository, https://github.com/Animatea/mongorunway
